{
  "ChangeBPMTimes": 1,
  "ChangeRhythmTimes": 1,
  "TotalNote": 338,
  "BandWavNum": 3,
  "BandWavDir": "D:\\download\\DanceEditor\\sound",
  "MotionStaTick": 0,
  "ChangeBPM": [
    {
      "Tick": 0,
      "Tempo": 13800,
      "TimePerTick": 0.036231884057971016
    }
  ],
  "ChangeRhythm": [
    {
      "Section": 1,
      "Beat": 4,
      "Tick": 0
    }
  ],
  "Track": [
    {
      "TrackID": 0,
      "NoteData": [
        { "Tick": 0, "EventID": 1, "SoundVol": 100, "ContTick": 0, "ContVal": 0, "Param1": 0 }
      ]
    },
    {
      "TrackID": 1,
      "NoteData": [
        { "Tick": 114, "EventID": 0, "SoundVol": 100, "ContTick": 0, "ContVal": 0, "Param1": 0 },
        { "Tick": 144, "EventID": 0, "SoundVol": 100, "ContTick": 0, "ContVal": 0, "Param1": 0 },
        { "Tick": 156, "EventID": 0, "SoundVol": 100, "ContTick": 0, "ContVal": 0, "Param1": 0 },
        { "Tick": 210, "EventID": 0, "SoundVol": 100, "ContTick": 0, "ContVal": 0, "Param1": 0 },
        { "Tick": 240, "EventID": 0, "SoundVol": 100, "ContTick": 0, "ContVal": 0, "Param1": 0 },
        { "Tick": 252, "EventID": 0, "SoundVol": 100, "ContTick": 0, "ContVal": 0, "Param1": 0 },
        { "Tick": 306, "EventID": 0, "SoundVol": 100, "ContTick": 0, "ContVal": 0, "Param1": 0 },
        { "Tick": 378, "EventID": 0, "SoundVol": 100, "ContTick": 0, "ContVal": 0, "Param1": 0 },
        { "Tick": 390, "EventID": 0, "SoundVol": 100, "ContTick": 0, "ContVal": 0, "Param1": 0 },
        { "Tick": 402, "EventID": 0, "SoundVol": 100, "ContTick": 0, "ContVal": 0, "Param1": 0 },
        { "Tick": 426, "EventID": 0, "SoundVol": 100, "ContTick": 0, "ContVal": 0, "Param1": 0 },
        { "Tick": 444, "EventID": 0, "SoundVol": 100, "ContTick": 0, "ContVal": 0, "Param1": 0 },
        { "Tick": 498, "EventID": 0, "SoundVol": 100, "ContTick": 0, "ContVal": 0, "Param1": 0 },
        { "Tick": 570, "EventID": 0, "SoundVol": 100, "ContTick": 0, "ContVal": 0, "Param1": 0 },
        { "Tick": 642, "EventID": 0, "SoundVol": 100, "ContTick": 0, "ContVal": 0, "Param1": 0 },
        { "Tick": 726, "EventID": 0, "SoundVol": 100, "ContTick": 0, "ContVal": 0, "Param1": 0 },
        { "Tick": 810, "EventID": 0, "SoundVol": 100, "ContTick": 0, "ContVal": 0, "Param1": 0 },
        { "Tick": 882, "EventID": 0, "SoundVol": 100, "ContTick": 0, "ContVal": 0, "Param1": 0 },
        { "Tick": 894, "EventID": 0, "SoundVol": 100, "ContTick": 0, "ContVal": 0, "Param1": 0 },
        { "Tick": 1026, "EventID": 0, "SoundVol": 100, "ContTick": 0, "ContVal": 0, "Param1": 0 },
        { "Tick": 1038, "EventID": 0, "SoundVol": 100, "ContTick": 0, "ContVal": 0, "Param1": 0 },
        { "Tick": 1074, "EventID": 0, "SoundVol": 100, "ContTick": 0, "ContVal": 0, "Param1": 0 },
        { "Tick": 1086, "EventID": 0, "SoundVol": 100, "ContTick": 0, "ContVal": 0, "Param1": 0 },
        { "Tick": 1290, "EventID": 0, "SoundVol": 100, "ContTick": 0, "ContVal": 0, "Param1": 0 },
        { "Tick": 1302, "EventID": 0, "SoundVol": 100, "ContTick": 0, "ContVal": 0, "Param1": 0 },
        { "Tick": 1314, "EventID": 0, "SoundVol": 100, "ContTick": 0, "ContVal": 0, "Param1": 0 },
        { "Tick": 1326, "EventID": 0, "SoundVol": 100, "ContTick": 0, "ContVal": 0, "Param1": 0 },
        { "Tick": 1338, "EventID": 0, "SoundVol": 100, "ContTick": 0, "ContVal": 0, "Param1": 0 },
        { "Tick": 1350, "EventID": 0, "SoundVol": 100, "ContTick": 0, "ContVal": 0, "Param1": 0 },
        { "Tick": 1362, "EventID": 0, "SoundVol": 100, "ContTick": 0, "ContVal": 0, "Param1": 0 },
        { "Tick": 1374, "EventID": 0, "SoundVol": 100, "ContTick": 0, "ContVal": 0, "Param1": 0 },
        { "Tick": 1410, "EventID": 0, "SoundVol": 100, "ContTick": 0, "ContVal": 0, "Param1": 0 },
        { "Tick": 1422, "EventID": 0, "SoundVol": 100, "ContTick": 0, "ContVal": 0, "Param1": 0 },
        { "Tick": 1434, "EventID": 0, "SoundVol": 100, "ContTick": 0, "ContVal": 0, "Param1": 0 },
        { "Tick": 1446, "EventID": 0, "SoundVol": 100, "ContTick": 0, "ContVal": 0, "Param1": 0 },
        { "Tick": 1458, "EventID": 0, "SoundVol": 100, "ContTick": 0, "ContVal": 0, "Param1": 0 },
        { "Tick": 1470, "EventID": 0, "SoundVol": 100, "ContTick": 0, "ContVal": 0, "Param1": 0 },
        { "Tick": 1542, "EventID": 0, "SoundVol": 100, "ContTick": 0, "ContVal": 0, "Param1": 0 },
        { "Tick": 1602, "EventID": 0, "SoundVol": 100, "ContTick": 0, "ContVal": 0, "Param1": 0 },
        { "Tick": 1608, "EventID": 0, "SoundVol": 100, "ContTick": 0, "ContVal": 0, "Param1": 0 },
        { "Tick": 1626, "EventID": 0, "SoundVol": 100, "ContTick": 0, "ContVal": 0, "Param1": 0 },
        { "Tick": 1698, "EventID": 0, "SoundVol": 100, "ContTick": 0, "ContVal": 0, "Param1": 0 },
        { "Tick": 1730, "EventID": 0, "SoundVol": 100, "ContTick": 0, "ContVal": 0, "Param1": 0 },
        { "Tick": 1742, "EventID": 0, "SoundVol": 100, "ContTick": 0, "ContVal": 0, "Param1": 0 },
        { "Tick": 1902, "EventID": 0, "SoundVol": 100, "ContTick": 0, "ContVal": 0, "Param1": 0 },
        { "Tick": 1914, "EventID": 0, "SoundVol": 100, "ContTick": 0, "ContVal": 0, "Param1": 0 },
        { "Tick": 1926, "EventID": 0, "SoundVol": 100, "ContTick": 0, "ContVal": 0, "Param1": 0 },
        { "Tick": 1938, "EventID": 0, "SoundVol": 100, "ContTick": 0, "ContVal": 0, "Param1": 0 },
        { "Tick": 1950, "EventID": 0, "SoundVol": 100, "ContTick": 0, "ContVal": 0, "Param1": 0 },
        { "Tick": 1962, "EventID": 0, "SoundVol": 100, "ContTick": 0, "ContVal": 0, "Param1": 0 },
        { "Tick": 2070, "EventID": 0, "SoundVol": 100, "ContTick": 0, "ContVal": 0, "Param1": 0 },
        { "Tick": 2076, "EventID": 0, "SoundVol": 100, "ContTick": 0, "ContVal": 0, "Param1": 0 },
        { "Tick": 2082, "EventID": 0, "SoundVol": 100, "ContTick": 0, "ContVal": 0, "Param1": 0 },
        { "Tick": 2178, "EventID": 0, "SoundVol": 100, "ContTick": 0, "ContVal": 0, "Param1": 0 },
        { "Tick": 2190, "EventID": 0, "SoundVol": 100, "ContTick": 0, "ContVal": 0, "Param1": 0 },
        { "Tick": 2202, "EventID": 0, "SoundVol": 100, "ContTick": 0, "ContVal": 0, "Param1": 0 },
        { "Tick": 2214, "EventID": 0, "SoundVol": 100, "ContTick": 0, "ContVal": 0, "Param1": 0 },
        { "Tick": 2226, "EventID": 0, "SoundVol": 100, "ContTick": 0, "ContVal": 0, "Param1": 0 },
        { "Tick": 2238, "EventID": 0, "SoundVol": 100, "ContTick": 0, "ContVal": 0, "Param1": 0 },
        { "Tick": 2250, "EventID": 0, "SoundVol": 100, "ContTick": 0, "ContVal": 0, "Param1": 0 },
        { "Tick": 2262, "EventID": 0, "SoundVol": 100, "ContTick": 0, "ContVal": 0, "Param1": 0 },
        { "Tick": 2274, "EventID": 0, "SoundVol": 100, "ContTick": 0, "ContVal": 0, "Param1": 0 },
        { "Tick": 2286, "EventID": 0, "SoundVol": 100, "ContTick": 0, "ContVal": 0, "Param1": 0 },
        { "Tick": 2298, "EventID": 0, "SoundVol": 100, "ContTick": 0, "ContVal": 0, "Param1": 0 },
        { "Tick": 2310, "EventID": 0, "SoundVol": 100, "ContTick": 0, "ContVal": 0, "Param1": 0 },
        { "Tick": 2466, "EventID": 0, "SoundVol": 100, "ContTick": 0, "ContVal": 0, "Param1": 0 },
        { "Tick": 2478, "EventID": 0, "SoundVol": 100, "ContTick": 0, "ContVal": 0, "Param1": 0 },
        { "Tick": 2490, "EventID": 0, "SoundVol": 100, "ContTick": 0, "ContVal": 0, "Param1": 0 },
        { "Tick": 2502, "EventID": 0, "SoundVol": 100, "ContTick": 0, "ContVal": 0, "Param1": 0 },
        { "Tick": 2526, "EventID": 0, "SoundVol": 100, "ContTick": 0, "ContVal": 0, "Param1": 0 },
        { "Tick": 2532, "EventID": 0, "SoundVol": 100, "ContTick": 0, "ContVal": 0, "Param1": 0 },
        { "Tick": 2538, "EventID": 0, "SoundVol": 100, "ContTick": 0, "ContVal": 0, "Param1": 0 }
      ]
    },
    {
      "TrackID": 2,
      "NoteData": [
        { "Tick": 114, "EventID": 0, "SoundVol": 100, "ContTick": 0, "ContVal": 0, "Param1": 0 },
        { "Tick": 144, "EventID": 0, "SoundVol": 100, "ContTick": 0, "ContVal": 0, "Param1": 0 },
        { "Tick": 156, "EventID": 0, "SoundVol": 100, "ContTick": 0, "ContVal": 0, "Param1": 0 },
        { "Tick": 210, "EventID": 0, "SoundVol": 100, "ContTick": 0, "ContVal": 0, "Param1": 0 },
        { "Tick": 240, "EventID": 0, "SoundVol": 100, "ContTick": 0, "ContVal": 0, "Param1": 0 },
        { "Tick": 252, "EventID": 0, "SoundVol": 100, "ContTick": 0, "ContVal": 0, "Param1": 0 },
        { "Tick": 318, "EventID": 0, "SoundVol": 100, "ContTick": 0, "ContVal": 0, "Param1": 0 },
        { "Tick": 366, "EventID": 0, "SoundVol": 100, "ContTick": 0, "ContVal": 0, "Param1": 0 },
        { "Tick": 390, "EventID": 0, "SoundVol": 100, "ContTick": 0, "ContVal": 0, "Param1": 0 },
        { "Tick": 402, "EventID": 0, "SoundVol": 100, "ContTick": 0, "ContVal": 0, "Param1": 0 },
        { "Tick": 426, "EventID": 0, "SoundVol": 100, "ContTick": 0, "ContVal": 0, "Param1": 0 },
        { "Tick": 444, "EventID": 0, "SoundVol": 100, "ContTick": 0, "ContVal": 0, "Param1": 0 },
        { "Tick": 510, "EventID": 0, "SoundVol": 100, "ContTick": 0, "ContVal": 0, "Param1": 0 },
        { "Tick": 558, "EventID": 0, "SoundVol": 100, "ContTick": 0, "ContVal": 0, "Param1": 0 },
        { "Tick": 582, "EventID": 0, "SoundVol": 100, "ContTick": 0, "ContVal": 0, "Param1": 0 },
        { "Tick": 630, "EventID": 0, "SoundVol": 100, "ContTick": 0, "ContVal": 0, "Param1": 0 },
        { "Tick": 654, "EventID": 0, "SoundVol": 100, "ContTick": 0, "ContVal": 0, "Param1": 0 },
        { "Tick": 714, "EventID": 0, "SoundVol": 100, "ContTick": 0, "ContVal": 0, "Param1": 0 },
        { "Tick": 738, "EventID": 0, "SoundVol": 100, "ContTick": 0, "ContVal": 0, "Param1": 0 },
        { "Tick": 798, "EventID": 0, "SoundVol": 100, "ContTick": 0, "ContVal": 0, "Param1": 0 },
        { "Tick": 822, "EventID": 0, "SoundVol": 100, "ContTick": 0, "ContVal": 0, "Param1": 0 },
        { "Tick": 870, "EventID": 0, "SoundVol": 100, "ContTick": 0, "ContVal": 0, "Param1": 0 },
        { "Tick": 882, "EventID": 0, "SoundVol": 100, "ContTick": 0, "ContVal": 0, "Param1": 0 },
        { "Tick": 894, "EventID": 0, "SoundVol": 100, "ContTick": 0, "ContVal": 0, "Param1": 0 },
        { "Tick": 1002, "EventID": 0, "SoundVol": 100, "ContTick": 0, "ContVal": 0, "Param1": 0 },
        { "Tick": 1008, "EventID": 0, "SoundVol": 100, "ContTick": 0, "ContVal": 0, "Param1": 0 },
        { "Tick": 1014, "EventID": 0, "SoundVol": 100, "ContTick": 0, "ContVal": 0, "Param1": 0 },
        { "Tick": 1050, "EventID": 0, "SoundVol": 100, "ContTick": 0, "ContVal": 0, "Param1": 0 },
        { "Tick": 1056, "EventID": 0, "SoundVol": 100, "ContTick": 0, "ContVal": 0, "Param1": 0 },
        { "Tick": 1062, "EventID": 0, "SoundVol": 100, "ContTick": 0, "ContVal": 0, "Param1": 0 },
        { "Tick": 1098, "EventID": 0, "SoundVol": 100, "ContTick": 0, "ContVal": 0, "Param1": 0 },
        { "Tick": 1104, "EventID": 0, "SoundVol": 100, "ContTick": 0, "ContVal": 0, "Param1": 0 },
        { "Tick": 1110, "EventID": 0, "SoundVol": 100, "ContTick": 0, "ContVal": 0, "Param1": 0 },
        { "Tick": 1146, "EventID": 0, "SoundVol": 100, "ContTick": 0, "ContVal": 0, "Param1": 0 },
        { "Tick": 1152, "EventID": 0, "SoundVol": 100, "ContTick": 0, "ContVal": 0, "Param1": 0 },
        { "Tick": 1158, "EventID": 0, "SoundVol": 100, "ContTick": 0, "ContVal": 0, "Param1": 0 },
        { "Tick": 1170, "EventID": 0, "SoundVol": 100, "ContTick": 0, "ContVal": 0, "Param1": 0 },
        { "Tick": 1182, "EventID": 0, "SoundVol": 100, "ContTick": 0, "ContVal": 0, "Param1": 0 },
        { "Tick": 1218, "EventID": 0, "SoundVol": 100, "ContTick": 0, "ContVal": 0, "Param1": 0 },
        { "Tick": 1230, "EventID": 0, "SoundVol": 100, "ContTick": 0, "ContVal": 0, "Param1": 0 },
        { "Tick": 1242, "EventID": 0, "SoundVol": 100, "ContTick": 0, "ContVal": 0, "Param1": 0 },
        { "Tick": 1254, "EventID": 0, "SoundVol": 100, "ContTick": 0, "ContVal": 0, "Param1": 0 },
        { "Tick": 1290, "EventID": 0, "SoundVol": 100, "ContTick": 0, "ContVal": 0, "Param1": 0 },
        { "Tick": 1302, "EventID": 0, "SoundVol": 100, "ContTick": 0, "ContVal": 0, "Param1": 0 },
        { "Tick": 1314, "EventID": 0, "SoundVol": 100, "ContTick": 0, "ContVal": 0, "Param1": 0 },
        { "Tick": 1326, "EventID": 0, "SoundVol": 100, "ContTick": 0, "ContVal": 0, "Param1": 0 },
        { "Tick": 1338, "EventID": 0, "SoundVol": 100, "ContTick": 0, "ContVal": 0, "Param1": 0 },
        { "Tick": 1350, "EventID": 0, "SoundVol": 100, "ContTick": 0, "ContVal": 0, "Param1": 0 },
        { "Tick": 1362, "EventID": 0, "SoundVol": 100, "ContTick": 0, "ContVal": 0, "Param1": 0 },
        { "Tick": 1374, "EventID": 0, "SoundVol": 100, "ContTick": 0, "ContVal": 0, "Param1": 0 },
        { "Tick": 1410, "EventID": 0, "SoundVol": 100, "ContTick": 0, "ContVal": 0, "Param1": 0 },
        { "Tick": 1422, "EventID": 0, "SoundVol": 100, "ContTick": 0, "ContVal": 0, "Param1": 0 },
        { "Tick": 1434, "EventID": 0, "SoundVol": 100, "ContTick": 0, "ContVal": 0, "Param1": 0 },
        { "Tick": 1446, "EventID": 0, "SoundVol": 100, "ContTick": 0, "ContVal": 0, "Param1": 0 },
        { "Tick": 1458, "EventID": 0, "SoundVol": 100, "ContTick": 0, "ContVal": 0, "Param1": 0 },
        { "Tick": 1470, "EventID": 0, "SoundVol": 100, "ContTick": 0, "ContVal": 0, "Param1": 0 },
        { "Tick": 1530, "EventID": 0, "SoundVol": 100, "ContTick": 0, "ContVal": 0, "Param1": 0 },
        { "Tick": 1554, "EventID": 0, "SoundVol": 100, "ContTick": 0, "ContVal": 0, "Param1": 0 },
        { "Tick": 1602, "EventID": 0, "SoundVol": 100, "ContTick": 0, "ContVal": 0, "Param1": 0 },
        { "Tick": 1608, "EventID": 0, "SoundVol": 100, "ContTick": 0, "ContVal": 0, "Param1": 0 },
        { "Tick": 1626, "EventID": 0, "SoundVol": 100, "ContTick": 0, "ContVal": 0, "Param1": 0 },
        { "Tick": 1878, "EventID": 0, "SoundVol": 100, "ContTick": 0, "ContVal": 0, "Param1": 0 },
        { "Tick": 1884, "EventID": 0, "SoundVol": 100, "ContTick": 0, "ContVal": 0, "Param1": 0 },
        { "Tick": 1890, "EventID": 0, "SoundVol": 100, "ContTick": 0, "ContVal": 0, "Param1": 0 },
        { "Tick": 1902, "EventID": 0, "SoundVol": 100, "ContTick": 0, "ContVal": 0, "Param1": 0 },
        { "Tick": 1914, "EventID": 0, "SoundVol": 100, "ContTick": 0, "ContVal": 0, "Param1": 0 },
        { "Tick": 1926, "EventID": 0, "SoundVol": 100, "ContTick": 0, "ContVal": 0, "Param1": 0 },
        { "Tick": 1938, "EventID": 0, "SoundVol": 100, "ContTick": 0, "ContVal": 0, "Param1": 0 },
        { "Tick": 1950, "EventID": 0, "SoundVol": 100, "ContTick": 0, "ContVal": 0, "Param1": 0 },
        { "Tick": 1962, "EventID": 0, "SoundVol": 100, "ContTick": 0, "ContVal": 0, "Param1": 0 },
        { "Tick": 1998, "EventID": 0, "SoundVol": 100, "ContTick": 0, "ContVal": 0, "Param1": 0 },
        { "Tick": 2010, "EventID": 0, "SoundVol": 100, "ContTick": 0, "ContVal": 0, "Param1": 0 },
        { "Tick": 2022, "EventID": 0, "SoundVol": 100, "ContTick": 0, "ContVal": 0, "Param1": 0 },
        { "Tick": 2034, "EventID": 0, "SoundVol": 100, "ContTick": 0, "ContVal": 0, "Param1": 0 },
        { "Tick": 2046, "EventID": 0, "SoundVol": 100, "ContTick": 0, "ContVal": 0, "Param1": 0 },
        { "Tick": 2058, "EventID": 0, "SoundVol": 100, "ContTick": 0, "ContVal": 0, "Param1": 0 },
        { "Tick": 2094, "EventID": 0, "SoundVol": 100, "ContTick": 0, "ContVal": 0, "Param1": 0 },
        { "Tick": 2106, "EventID": 0, "SoundVol": 100, "ContTick": 0, "ContVal": 0, "Param1": 0 },
        { "Tick": 2118, "EventID": 0, "SoundVol": 100, "ContTick": 0, "ContVal": 0, "Param1": 0 },
        { "Tick": 2130, "EventID": 0, "SoundVol": 100, "ContTick": 0, "ContVal": 0, "Param1": 0 },
        { "Tick": 2142, "EventID": 0, "SoundVol": 100, "ContTick": 0, "ContVal": 0, "Param1": 0 },
        { "Tick": 2154, "EventID": 0, "SoundVol": 100, "ContTick": 0, "ContVal": 0, "Param1": 0 },
        { "Tick": 2166, "EventID": 0, "SoundVol": 100, "ContTick": 0, "ContVal": 0, "Param1": 0 },
        { "Tick": 2178, "EventID": 0, "SoundVol": 100, "ContTick": 0, "ContVal": 0, "Param1": 0 },
        { "Tick": 2190, "EventID": 0, "SoundVol": 100, "ContTick": 0, "ContVal": 0, "Param1": 0 },
        { "Tick": 2202, "EventID": 0, "SoundVol": 100, "ContTick": 0, "ContVal": 0, "Param1": 0 },
        { "Tick": 2214, "EventID": 0, "SoundVol": 100, "ContTick": 0, "ContVal": 0, "Param1": 0 },
        { "Tick": 2232, "EventID": 0, "SoundVol": 100, "ContTick": 0, "ContVal": 0, "Param1": 0 },
        { "Tick": 2244, "EventID": 0, "SoundVol": 100, "ContTick": 0, "ContVal": 0, "Param1": 0 },
        { "Tick": 2256, "EventID": 0, "SoundVol": 100, "ContTick": 0, "ContVal": 0, "Param1": 0 },
        { "Tick": 2268, "EventID": 0, "SoundVol": 100, "ContTick": 0, "ContVal": 0, "Param1": 0 },
        { "Tick": 2280, "EventID": 0, "SoundVol": 100, "ContTick": 0, "ContVal": 0, "Param1": 0 },
        { "Tick": 2292, "EventID": 0, "SoundVol": 100, "ContTick": 0, "ContVal": 0, "Param1": 0 },
        { "Tick": 2304, "EventID": 0, "SoundVol": 100, "ContTick": 0, "ContVal": 0, "Param1": 0 },
        { "Tick": 2310, "EventID": 0, "SoundVol": 100, "ContTick": 0, "ContVal": 0, "Param1": 0 },
        { "Tick": 2322, "EventID": 0, "SoundVol": 100, "ContTick": 0, "ContVal": 0, "Param1": 0 },
        { "Tick": 2334, "EventID": 0, "SoundVol": 100, "ContTick": 0, "ContVal": 0, "Param1": 0 },
        { "Tick": 2346, "EventID": 0, "SoundVol": 100, "ContTick": 0, "ContVal": 0, "Param1": 0 },
        { "Tick": 2358, "EventID": 0, "SoundVol": 100, "ContTick": 0, "ContVal": 0, "Param1": 0 },
        { "Tick": 2370, "EventID": 0, "SoundVol": 100, "ContTick": 0, "ContVal": 0, "Param1": 0 },
        { "Tick": 2382, "EventID": 0, "SoundVol": 100, "ContTick": 0, "ContVal": 0, "Param1": 0 },
        { "Tick": 2394, "EventID": 0, "SoundVol": 100, "ContTick": 0, "ContVal": 0, "Param1": 0 },
        { "Tick": 2406, "EventID": 0, "SoundVol": 100, "ContTick": 0, "ContVal": 0, "Param1": 0 },
        { "Tick": 2442, "EventID": 0, "SoundVol": 100, "ContTick": 0, "ContVal": 0, "Param1": 0 },
        { "Tick": 2454, "EventID": 0, "SoundVol": 100, "ContTick": 0, "ContVal": 0, "Param1": 0 },
        { "Tick": 2466, "EventID": 0, "SoundVol": 100, "ContTick": 0, "ContVal": 0, "Param1": 0 },
        { "Tick": 2478, "EventID": 0, "SoundVol": 100, "ContTick": 0, "ContVal": 0, "Param1": 0 },
        { "Tick": 2490, "EventID": 0, "SoundVol": 100, "ContTick": 0, "ContVal": 0, "Param1": 0 },
        { "Tick": 2502, "EventID": 0, "SoundVol": 100, "ContTick": 0, "ContVal": 0, "Param1": 0 },
        { "Tick": 2526, "EventID": 0, "SoundVol": 100, "ContTick": 0, "ContVal": 0, "Param1": 0 },
        { "Tick": 2532, "EventID": 0, "SoundVol": 100, "ContTick": 0, "ContVal": 0, "Param1": 0 },
        { "Tick": 2538, "EventID": 0, "SoundVol": 100, "ContTick": 0, "ContVal": 0, "Param1": 0 }
      ]
    },
    {
      "TrackID": 3,
      "NoteData": [
        { "Tick": 114, "EventID": 0, "SoundVol": 100, "ContTick": 0, "ContVal": 0, "Param1": 0 },
        { "Tick": 144, "EventID": 0, "SoundVol": 100, "ContTick": 0, "ContVal": 0, "Param1": 0 },
        { "Tick": 156, "EventID": 0, "SoundVol": 100, "ContTick": 0, "ContVal": 0, "Param1": 0 },
        { "Tick": 210, "EventID": 0, "SoundVol": 100, "ContTick": 0, "ContVal": 0, "Param1": 0 },
        { "Tick": 240, "EventID": 0, "SoundVol": 100, "ContTick": 0, "ContVal": 0, "Param1": 0 },
        { "Tick": 252, "EventID": 0, "SoundVol": 100, "ContTick": 0, "ContVal": 0, "Param1": 0 },
        { "Tick": 330, "EventID": 0, "SoundVol": 100, "ContTick": 0, "ContVal": 0, "Param1": 0 },
        { "Tick": 354, "EventID": 0, "SoundVol": 100, "ContTick": 0, "ContVal": 0, "Param1": 0 },
        { "Tick": 396, "EventID": 0, "SoundVol": 100, "ContTick": 0, "ContVal": 0, "Param1": 0 },
        { "Tick": 426, "EventID": 0, "SoundVol": 100, "ContTick": 0, "ContVal": 0, "Param1": 0 },
        { "Tick": 444, "EventID": 0, "SoundVol": 100, "ContTick": 0, "ContVal": 0, "Param1": 0 },
        { "Tick": 522, "EventID": 0, "SoundVol": 100, "ContTick": 0, "ContVal": 0, "Param1": 0 },
        { "Tick": 546, "EventID": 0, "SoundVol": 100, "ContTick": 0, "ContVal": 0, "Param1": 0 },
        { "Tick": 588, "EventID": 0, "SoundVol": 100, "ContTick": 0, "ContVal": 0, "Param1": 0 },
        { "Tick": 594, "EventID": 0, "SoundVol": 100, "ContTick": 0, "ContVal": 0, "Param1": 0 },
        { "Tick": 618, "EventID": 0, "SoundVol": 100, "ContTick": 0, "ContVal": 0, "Param1": 0 },
        { "Tick": 666, "EventID": 0, "SoundVol": 100, "ContTick": 0, "ContVal": 0, "Param1": 0 },
        { "Tick": 702, "EventID": 0, "SoundVol": 100, "ContTick": 0, "ContVal": 0, "Param1": 0 },
        { "Tick": 750, "EventID": 0, "SoundVol": 100, "ContTick": 0, "ContVal": 0, "Param1": 0 },
        { "Tick": 774, "EventID": 0, "SoundVol": 100, "ContTick": 0, "ContVal": 0, "Param1": 0 },
        { "Tick": 780, "EventID": 0, "SoundVol": 100, "ContTick": 0, "ContVal": 0, "Param1": 0 },
        { "Tick": 786, "EventID": 0, "SoundVol": 100, "ContTick": 0, "ContVal": 0, "Param1": 0 },
        { "Tick": 834, "EventID": 0, "SoundVol": 100, "ContTick": 0, "ContVal": 0, "Param1": 0 },
        { "Tick": 858, "EventID": 0, "SoundVol": 100, "ContTick": 0, "ContVal": 0, "Param1": 0 },
        { "Tick": 906, "EventID": 0, "SoundVol": 100, "ContTick": 0, "ContVal": 0, "Param1": 0 },
        { "Tick": 912, "EventID": 0, "SoundVol": 100, "ContTick": 0, "ContVal": 0, "Param1": 0 },
        { "Tick": 918, "EventID": 0, "SoundVol": 100, "ContTick": 0, "ContVal": 0, "Param1": 0 },
        { "Tick": 954, "EventID": 0, "SoundVol": 100, "ContTick": 0, "ContVal": 0, "Param1": 0 },
        { "Tick": 960, "EventID": 0, "SoundVol": 100, "ContTick": 0, "ContVal": 0, "Param1": 0 },
        { "Tick": 966, "EventID": 0, "SoundVol": 100, "ContTick": 0, "ContVal": 0, "Param1": 0 },
        { "Tick": 978, "EventID": 0, "SoundVol": 100, "ContTick": 0, "ContVal": 0, "Param1": 0 },
        { "Tick": 990, "EventID": 0, "SoundVol": 100, "ContTick": 0, "ContVal": 0, "Param1": 0 },
        { "Tick": 1074, "EventID": 0, "SoundVol": 100, "ContTick": 0, "ContVal": 0, "Param1": 0 },
        { "Tick": 1086, "EventID": 0, "SoundVol": 100, "ContTick": 0, "ContVal": 0, "Param1": 0 },
        { "Tick": 1194, "EventID": 0, "SoundVol": 100, "ContTick": 0, "ContVal": 0, "Param1": 0 },
        { "Tick": 1200, "EventID": 0, "SoundVol": 100, "ContTick": 0, "ContVal": 0, "Param1": 0 },
        { "Tick": 1206, "EventID": 0, "SoundVol": 100, "ContTick": 0, "ContVal": 0, "Param1": 0 },
        { "Tick": 1290, "EventID": 0, "SoundVol": 100, "ContTick": 0, "ContVal": 0, "Param1": 0 },
        { "Tick": 1302, "EventID": 0, "SoundVol": 100, "ContTick": 0, "ContVal": 0, "Param1": 0 },
        { "Tick": 1386, "EventID": 0, "SoundVol": 100, "ContTick": 0, "ContVal": 0, "Param1": 0 },
        { "Tick": 1398, "EventID": 0, "SoundVol": 100, "ContTick": 0, "ContVal": 0, "Param1": 0 },
        { "Tick": 1482, "EventID": 0, "SoundVol": 100, "ContTick": 0, "ContVal": 0, "Param1": 0 },
        { "Tick": 1494, "EventID": 0, "SoundVol": 100, "ContTick": 0, "ContVal": 0, "Param1": 0 },
        { "Tick": 1518, "EventID": 0, "SoundVol": 100, "ContTick": 0, "ContVal": 0, "Param1": 0 },
        { "Tick": 1566, "EventID": 0, "SoundVol": 100, "ContTick": 0, "ContVal": 0, "Param1": 0 },
        { "Tick": 1590, "EventID": 0, "SoundVol": 100, "ContTick": 0, "ContVal": 0, "Param1": 0 },
        { "Tick": 1614, "EventID": 0, "SoundVol": 100, "ContTick": 0, "ContVal": 0, "Param1": 0 },
        { "Tick": 1620, "EventID": 0, "SoundVol": 100, "ContTick": 0, "ContVal": 0, "Param1": 0 },
        { "Tick": 1626, "EventID": 0, "SoundVol": 100, "ContTick": 0, "ContVal": 0, "Param1": 0 },
        { "Tick": 1794, "EventID": 0, "SoundVol": 100, "ContTick": 0, "ContVal": 0, "Param1": 0 },
        { "Tick": 1806, "EventID": 0, "SoundVol": 100, "ContTick": 0, "ContVal": 0, "Param1": 0 },
        { "Tick": 1818, "EventID": 0, "SoundVol": 100, "ContTick": 0, "ContVal": 0, "Param1": 0 },
        { "Tick": 1830, "EventID": 0, "SoundVol": 100, "ContTick": 0, "ContVal": 0, "Param1": 0 },
        { "Tick": 1842, "EventID": 0, "SoundVol": 100, "ContTick": 0, "ContVal": 0, "Param1": 0 },
        { "Tick": 1854, "EventID": 0, "SoundVol": 100, "ContTick": 0, "ContVal": 0, "Param1": 0 },
        { "Tick": 1866, "EventID": 0, "SoundVol": 100, "ContTick": 0, "ContVal": 0, "Param1": 0 },
        { "Tick": 1974, "EventID": 0, "SoundVol": 100, "ContTick": 0, "ContVal": 0, "Param1": 0 },
        { "Tick": 1980, "EventID": 0, "SoundVol": 100, "ContTick": 0, "ContVal": 0, "Param1": 0 },
        { "Tick": 1986, "EventID": 0, "SoundVol": 100, "ContTick": 0, "ContVal": 0, "Param1": 0 },
        { "Tick": 2094, "EventID": 0, "SoundVol": 100, "ContTick": 0, "ContVal": 0, "Param1": 0 },
        { "Tick": 2106, "EventID": 0, "SoundVol": 100, "ContTick": 0, "ContVal": 0, "Param1": 0 },
        { "Tick": 2118, "EventID": 0, "SoundVol": 100, "ContTick": 0, "ContVal": 0, "Param1": 0 },
        { "Tick": 2130, "EventID": 0, "SoundVol": 100, "ContTick": 0, "ContVal": 0, "Param1": 0 },
        { "Tick": 2142, "EventID": 0, "SoundVol": 100, "ContTick": 0, "ContVal": 0, "Param1": 0 },
        { "Tick": 2154, "EventID": 0, "SoundVol": 100, "ContTick": 0, "ContVal": 0, "Param1": 0 },
        { "Tick": 2166, "EventID": 0, "SoundVol": 100, "ContTick": 0, "ContVal": 0, "Param1": 0 },
        { "Tick": 2178, "EventID": 0, "SoundVol": 100, "ContTick": 0, "ContVal": 0, "Param1": 0 },
        { "Tick": 2190, "EventID": 0, "SoundVol": 100, "ContTick": 0, "ContVal": 0, "Param1": 0 },
        { "Tick": 2202, "EventID": 0, "SoundVol": 100, "ContTick": 0, "ContVal": 0, "Param1": 0 },
        { "Tick": 2214, "EventID": 0, "SoundVol": 100, "ContTick": 0, "ContVal": 0, "Param1": 0 },
        { "Tick": 2328, "EventID": 0, "SoundVol": 100, "ContTick": 0, "ContVal": 0, "Param1": 0 },
        { "Tick": 2340, "EventID": 0, "SoundVol": 100, "ContTick": 0, "ContVal": 0, "Param1": 0 },
        { "Tick": 2352, "EventID": 0, "SoundVol": 100, "ContTick": 0, "ContVal": 0, "Param1": 0 },
        { "Tick": 2364, "EventID": 0, "SoundVol": 100, "ContTick": 0, "ContVal": 0, "Param1": 0 },
        { "Tick": 2376, "EventID": 0, "SoundVol": 100, "ContTick": 0, "ContVal": 0, "Param1": 0 },
        { "Tick": 2388, "EventID": 0, "SoundVol": 100, "ContTick": 0, "ContVal": 0, "Param1": 0 },
        { "Tick": 2400, "EventID": 0, "SoundVol": 100, "ContTick": 0, "ContVal": 0, "Param1": 0 },
        { "Tick": 2406, "EventID": 0, "SoundVol": 100, "ContTick": 0, "ContVal": 0, "Param1": 0 },
        { "Tick": 2418, "EventID": 0, "SoundVol": 100, "ContTick": 0, "ContVal": 0, "Param1": 0 },
        { "Tick": 2430, "EventID": 0, "SoundVol": 100, "ContTick": 0, "ContVal": 0, "Param1": 0 },
        { "Tick": 2442, "EventID": 0, "SoundVol": 100, "ContTick": 0, "ContVal": 0, "Param1": 0 },
        { "Tick": 2454, "EventID": 0, "SoundVol": 100, "ContTick": 0, "ContVal": 0, "Param1": 0 },
        { "Tick": 2514, "EventID": 0, "SoundVol": 100, "ContTick": 0, "ContVal": 0, "Param1": 0 },
        { "Tick": 2520, "EventID": 0, "SoundVol": 100, "ContTick": 0, "ContVal": 0, "Param1": 0 },
        { "Tick": 2538, "EventID": 0, "SoundVol": 100, "ContTick": 0, "ContVal": 0, "Param1": 0 }
      ]
    },
    {
      "TrackID": 4,
      "NoteData": [
        { "Tick": 18, "EventID": 0, "SoundVol": 100, "ContTick": 0, "ContVal": 0, "Param1": 0 },
        { "Tick": 30, "EventID": 0, "SoundVol": 100, "ContTick": 0, "ContVal": 0, "Param1": 0 },
        { "Tick": 42, "EventID": 0, "SoundVol": 100, "ContTick": 0, "ContVal": 0, "Param1": 0 },
        { "Tick": 48, "EventID": 0, "SoundVol": 100, "ContTick": 0, "ContVal": 0, "Param1": 0 },
        { "Tick": 54, "EventID": 0, "SoundVol": 100, "ContTick": 0, "ContVal": 0, "Param1": 0 },
        { "Tick": 66, "EventID": 0, "SoundVol": 100, "ContTick": 0, "ContVal": 0, "Param1": 0 },
        { "Tick": 78, "EventID": 0, "SoundVol": 100, "ContTick": 0, "ContVal": 0, "Param1": 0 },
        { "Tick": 90, "EventID": 0, "SoundVol": 100, "ContTick": 0, "ContVal": 0, "Param1": 0 },
        { "Tick": 96, "EventID": 0, "SoundVol": 100, "ContTick": 0, "ContVal": 0, "Param1": 0 },
        { "Tick": 102, "EventID": 0, "SoundVol": 100, "ContTick": 0, "ContVal": 0, "Param1": 0 },
        { "Tick": 114, "EventID": 0, "SoundVol": 100, "ContTick": 0, "ContVal": 0, "Param1": 0 },
        { "Tick": 144, "EventID": 0, "SoundVol": 100, "ContTick": 0, "ContVal": 0, "Param1": 0 },
        { "Tick": 156, "EventID": 0, "SoundVol": 100, "ContTick": 0, "ContVal": 0, "Param1": 0 },
        { "Tick": 210, "EventID": 0, "SoundVol": 100, "ContTick": 0, "ContVal": 0, "Param1": 0 },
        { "Tick": 240, "EventID": 0, "SoundVol": 100, "ContTick": 0, "ContVal": 0, "Param1": 0 },
        { "Tick": 252, "EventID": 0, "SoundVol": 100, "ContTick": 0, "ContVal": 0, "Param1": 0 },
        { "Tick": 342, "EventID": 0, "SoundVol": 100, "ContTick": 0, "ContVal": 0, "Param1": 0 },
        { "Tick": 396, "EventID": 0, "SoundVol": 100, "ContTick": 0, "ContVal": 0, "Param1": 0 },
        { "Tick": 426, "EventID": 0, "SoundVol": 100, "ContTick": 0, "ContVal": 0, "Param1": 0 },
        { "Tick": 444, "EventID": 0, "SoundVol": 100, "ContTick": 0, "ContVal": 0, "Param1": 0 },
        { "Tick": 534, "EventID": 0, "SoundVol": 100, "ContTick": 0, "ContVal": 0, "Param1": 0 },
        { "Tick": 606, "EventID": 0, "SoundVol": 100, "ContTick": 0, "ContVal": 0, "Param1": 0 },
        { "Tick": 678, "EventID": 0, "SoundVol": 100, "ContTick": 0, "ContVal": 0, "Param1": 0 },
        { "Tick": 684, "EventID": 0, "SoundVol": 100, "ContTick": 0, "ContVal": 0, "Param1": 0 },
        { "Tick": 690, "EventID": 0, "SoundVol": 100, "ContTick": 0, "ContVal": 0, "Param1": 0 },
        { "Tick": 762, "EventID": 0, "SoundVol": 100, "ContTick": 0, "ContVal": 0, "Param1": 0 },
        { "Tick": 846, "EventID": 0, "SoundVol": 100, "ContTick": 0, "ContVal": 0, "Param1": 0 },
        { "Tick": 930, "EventID": 0, "SoundVol": 100, "ContTick": 0, "ContVal": 0, "Param1": 0 },
        { "Tick": 942, "EventID": 0, "SoundVol": 100, "ContTick": 0, "ContVal": 0, "Param1": 0 },
        { "Tick": 978, "EventID": 0, "SoundVol": 100, "ContTick": 0, "ContVal": 0, "Param1": 0 },
        { "Tick": 990, "EventID": 0, "SoundVol": 100, "ContTick": 0, "ContVal": 0, "Param1": 0 },
        { "Tick": 1122, "EventID": 0, "SoundVol": 100, "ContTick": 0, "ContVal": 0, "Param1": 0 },
        { "Tick": 1134, "EventID": 0, "SoundVol": 100, "ContTick": 0, "ContVal": 0, "Param1": 0 },
        { "Tick": 1170, "EventID": 0, "SoundVol": 100, "ContTick": 0, "ContVal": 0, "Param1": 0 },
        { "Tick": 1182, "EventID": 0, "SoundVol": 100, "ContTick": 0, "ContVal": 0, "Param1": 0 },
        { "Tick": 1290, "EventID": 0, "SoundVol": 100, "ContTick": 0, "ContVal": 0, "Param1": 0 },
        { "Tick": 1302, "EventID": 0, "SoundVol": 100, "ContTick": 0, "ContVal": 0, "Param1": 0 },
        { "Tick": 1392, "EventID": 0, "SoundVol": 100, "ContTick": 0, "ContVal": 0, "Param1": 0 },
        { "Tick": 1488, "EventID": 0, "SoundVol": 100, "ContTick": 0, "ContVal": 0, "Param1": 0 },
        { "Tick": 1506, "EventID": 0, "SoundVol": 100, "ContTick": 0, "ContVal": 0, "Param1": 0 },
        { "Tick": 1578, "EventID": 0, "SoundVol": 100, "ContTick": 0, "ContVal": 0, "Param1": 0 },
        { "Tick": 1614, "EventID": 0, "SoundVol": 100, "ContTick": 0, "ContVal": 0, "Param1": 0 },
        { "Tick": 1620, "EventID": 0, "SoundVol": 100, "ContTick": 0, "ContVal": 0, "Param1": 0 },
        { "Tick": 1626, "EventID": 0, "SoundVol": 100, "ContTick": 0, "ContVal": 0, "Param1": 0 },
        { "Tick": 1698, "EventID": 0, "SoundVol": 100, "ContTick": 0, "ContVal": 0, "Param1": 0 },
        { "Tick": 1730, "EventID": 0, "SoundVol": 100, "ContTick": 0, "ContVal": 0, "Param1": 0 },
        { "Tick": 1742, "EventID": 0, "SoundVol": 100, "ContTick": 0, "ContVal": 0, "Param1": 0 },
        { "Tick": 1794, "EventID": 0, "SoundVol": 100, "ContTick": 0, "ContVal": 0, "Param1": 0 },
        { "Tick": 1806, "EventID": 0, "SoundVol": 100, "ContTick": 0, "ContVal": 0, "Param1": 0 },
        { "Tick": 1818, "EventID": 0, "SoundVol": 100, "ContTick": 0, "ContVal": 0, "Param1": 0 },
        { "Tick": 1830, "EventID": 0, "SoundVol": 100, "ContTick": 0, "ContVal": 0, "Param1": 0 },
        { "Tick": 1842, "EventID": 0, "SoundVol": 100, "ContTick": 0, "ContVal": 0, "Param1": 0 },
        { "Tick": 1854, "EventID": 0, "SoundVol": 100, "ContTick": 0, "ContVal": 0, "Param1": 0 },
        { "Tick": 1866, "EventID": 0, "SoundVol": 100, "ContTick": 0, "ContVal": 0, "Param1": 0 },
        { "Tick": 1998, "EventID": 0, "SoundVol": 100, "ContTick": 0, "ContVal": 0, "Param1": 0 },
        { "Tick": 2010, "EventID": 0, "SoundVol": 100, "ContTick": 0, "ContVal": 0, "Param1": 0 },
        { "Tick": 2022, "EventID": 0, "SoundVol": 100, "ContTick": 0, "ContVal": 0, "Param1": 0 },
        { "Tick": 2034, "EventID": 0, "SoundVol": 100, "ContTick": 0, "ContVal": 0, "Param1": 0 },
        { "Tick": 2046, "EventID": 0, "SoundVol": 100, "ContTick": 0, "ContVal": 0, "Param1": 0 },
        { "Tick": 2058, "EventID": 0, "SoundVol": 100, "ContTick": 0, "ContVal": 0, "Param1": 0 },
        { "Tick": 2178, "EventID": 0, "SoundVol": 100, "ContTick": 0, "ContVal": 0, "Param1": 0 },
        { "Tick": 2190, "EventID": 0, "SoundVol": 100, "ContTick": 0, "ContVal": 0, "Param1": 0 },
        { "Tick": 2202, "EventID": 0, "SoundVol": 100, "ContTick": 0, "ContVal": 0, "Param1": 0 },
        { "Tick": 2214, "EventID": 0, "SoundVol": 100, "ContTick": 0, "ContVal": 0, "Param1": 0 },
        { "Tick": 2418, "EventID": 0, "SoundVol": 100, "ContTick": 0, "ContVal": 0, "Param1": 0 },
        { "Tick": 2430, "EventID": 0, "SoundVol": 100, "ContTick": 0, "ContVal": 0, "Param1": 0 },
        { "Tick": 2514, "EventID": 0, "SoundVol": 100, "ContTick": 0, "ContVal": 0, "Param1": 0 },
        { "Tick": 2520, "EventID": 0, "SoundVol": 100, "ContTick": 0, "ContVal": 0, "Param1": 0 },
        { "Tick": 2538, "EventID": 0, "SoundVol": 100, "ContTick": 0, "ContVal": 0, "Param1": 0 }
      ]
    },
    {
      "TrackID": 5,
      "NoteData": []
    }
  ],
  "BandWav": [
    {
      "WavID": 0, "Path": "beats" },
    { "WavID": 1, "Path": "poli" },
    { "WavID": 2, "Path": "superwings"
    }
  ]
}